MANIFEST.in
README.md
kaleidoscope-config.h
kaleidoscope.c
kaleidoscope.cpp
kaleidoscope.h
kaleidoscope.hpp
kaleidoscope.pxd
kaleidoscope.pyx
pyproject.toml
setup.py
LibKaleidoscope.egg-info/PKG-INFO
LibKaleidoscope.egg-info/SOURCES.txt
LibKaleidoscope.egg-info/dependency_links.txt
LibKaleidoscope.egg-info/top_level.txt