Metadata-Version: 2.4
Name: LibKaleidoscope
Version: 1.4.2
Summary: A library to create kaleidoscope effect on images.
Home-page: https://egecetin.github.io/libKaleidoscope/
Download-URL: https://github.com/egecetin/libKaleidoscope/releases
Author: egecetin
Author-email: egecetin@hotmail.com.tr
Maintainer: egecetin
Maintainer-email: egecetin@hotmail.com.tr
License: MIT License
Keywords: image-processing,video-processing,image-manipulation,image-filtering,video-filtering
Platform: any
Classifier: License :: OSI Approved :: MIT License
Classifier: Operating System :: MacOS
Classifier: Operating System :: Microsoft
Classifier: Operating System :: OS Independent
Classifier: Operating System :: Unix
Classifier: Programming Language :: C
Classifier: Programming Language :: Cython
Classifier: Topic :: Scientific/Engineering :: Image Processing
Dynamic: author
Dynamic: author-email
Dynamic: classifier
Dynamic: description
Dynamic: description-content-type
Dynamic: download-url
Dynamic: home-page
Dynamic: keywords
Dynamic: license
Dynamic: maintainer
Dynamic: maintainer-email
Dynamic: platform
Dynamic: summary
